memrise_audio_uploader/__init__.py
memrise_audio_uploader/__main__.py
memrise_audio_uploader/cli.py
memrise_audio_uploader/lib/__init__.py
memrise_audio_uploader/lib/memrise/__init__.py
memrise_audio_uploader/lib/memrise/client.py
memrise_audio_uploader/lib/memrise/exceptions.py
memrise_audio_uploader/lib/memrise/models.py
memrise_audio_uploader/lib/synthesizator.py
memrise_audio_uploader-0.3.1.dist-info/LICENSE
memrise_audio_uploader-0.3.1.dist-info/METADATA
memrise_audio_uploader-0.3.1.dist-info/WHEEL
memrise_audio_uploader-0.3.1.dist-info/RECORD
