Metadata-Version: 2.1
Name: memrise_audio_uploader
Version: 0.3.1
Summary: Memrise audio uploader
Home-page: https://github.com/ollipa/memrise-audio-uploader
License: MIT
Author: Olli Paakkunainen
Author-email: olli@paakkunainen.fi
Requires-Python: >=3.8,<4.0
Classifier: License :: OSI Approved :: MIT License
Classifier: Programming Language :: Python :: 3
Classifier: Programming Language :: Python :: 3.8
Classifier: Programming Language :: Python :: 3.9
Classifier: Programming Language :: Python :: 3.10
Classifier: Programming Language :: Python :: 3.11
Requires-Dist: google-cloud-texttospeech (>=2.14.0,<3.0.0)
Requires-Dist: lxml (>=4.8.0,<5.0.0)
Requires-Dist: pydantic (>=2.0.0,<3.0.0)
Requires-Dist: pydantic-settings (>=2.0.0,<3.0.0)
Requires-Dist: python-dotenv (>=1.0.0,<2.0.0)
Requires-Dist: requests (>=2.27.0,<3.0.0)
Project-URL: Repository, https://github.com/ollipa/memrise-audio-uploader
